{
    "Date": "XX.XX.XXX",
    "patient_information": {
        "patient_id": null,
        "patient_name": "[FILL]",
        "patient_sex": "[FILL]",
        "patient_age": null
    },
    "test_results": [
        {
            "test_name": "DR 1 Ro",
            "result_value": "7001000",
            "unit_of_measurement": "a B Paolel",
            "reference_range": null
        },
        {
            "test_name": "SVepelh",
            "result_value": "29",
            "unit_of_measurement": "5 0 SVoo",
            "reference_range": null
        },
        {
            "test_name": "F PO U U0o",
            "result_value": "2 U 52",
            "unit_of_measurement": null,
            "reference_range": null
        }
    ]
}