{
    "Date": null,
    "patient_information": {
        "patient_id": null,
        "patient_name": "hipotctico",
        "patient_sex": null,
        "patient_age": null
    },
    "test_results": [
        {
            "test_name": "hemmoglagns",
            "result_value": "se r",
            "unit_of_measurement": null,
            "reference_range": null
        },
        {
            "test_name": "prolainn",
            "result_value": "s e",
            "unit_of_measurement": null,
            "reference_range": null
        },
        {
            "test_name": "bimsbina",
            "result_value": "s s s s",
            "unit_of_measurement": null,
            "reference_range": null
        }
    ]
}