{
    "Date": "XX.XX.XXXX",
    "patient_information": {
        "patient_id": "thcarei 0123456789",
        "patient_name": "age m complex patel",
        "patient_sex": "male",
        "patient_age": "21 years"
    },
    "test_results": [
        {
            "test_name": "hemoglobin at type obin",
            "result_value": "889578",
            "unit_of_measurement": "",
            "reference_range": ""
        },
        {
            "test_name": "total hbl hiren result rbc blood shah blood blood wwws count packed drlogy count indices registereds com mean cell volume cbcy calcuaned collectedt corpuscular volume on reference mch reported",
            "result_value": "",
            "unit_of_measurement": "",
            "reference_range": ""
        },
        {
            "test_name": "corpuscular volume",
            "result_value": "02131 cuicuated ons pcvy 52 pms",
            "unit_of_measurement": "",
            "reference_range": ""
        },
        {
            "test_name": "mean cell volume",
            "result_value": "0z cachc ons pm decs",
            "unit_of_measurement": "",
            "reference_range": ""
        },
        {
            "test_name": "rdw low decs imcvy",
            "result_value": "57 x dec 130 s wbc",
            "unit_of_measurement": "",
            "reference_range": ""
        },
        {
            "test_name": "neutrophils high",
            "result_value": "52 8",
            "unit_of_measurement": "",
            "reference_range": ""
        },
        {
            "test_name": "lymphocytes",
            "result_value": "40 136 gial wbc s0 eosinophils e5 count monocytes",
            "unit_of_measurement": "",
            "reference_range": ""
        },
        {
            "test_name": "eosinophils",
            "result_value": "e5 count monocytes",
            "unit_of_measurement": "",
            "reference_range": ""
        },
        {
            "test_name": "basophils",
            "result_value": "52 325 pla",
            "unit_of_measurement": "",
            "reference_range": ""
        },
        {
            "test_name": "platelet",
            "result_value": "60 telet platelet 345 116 fl count count 140 400011000 instruments pg interpretations gidl fully s0 o automated 62 thanks",
            "unit_of_measurement": "",
            "reference_range": ""
        },
        {
            "test_name": "neutrophils high",
            "result_value": "",
            "unit_of_measurement": "",
            "reference_range": ""
        }
    ]
}