{
    "Date": null,
    "patient_information": {
        "patient_id": null,
        "patient_name": null,
        "patient_sex": null,
        "patient_age": null
    },
    "test_results": [
        {
            "test_name": "HEMOGRAMA SERIE ROJA",
            "result_value": 4.75,
            "unit_of_measurement": null,
            "reference_range": null
        },
        {
            "test_name": "HEMOGLOBINA A-",
            "result_value": 13.3,
            "unit_of_measurement": null,
            "reference_range": null
        },
        {
            "test_name": "Hematocrito g/L",
            "result_value": 12.0,
            "unit_of_measurement": "g/L",
            "reference_range": "10 - 39.5"
        },
        {
            "test_name": "V.C.M.",
            "result_value": 36.0,
            "unit_of_measurement": "%",
            "reference_range": "36.0 - 47.0"
        },
        {
            "test_name": "H.C,M.",
            "result_value": 80.0,
            "unit_of_measurement": "IL",
            "reference_range": null
        },
        {
            "test_name": "C.H,CML ",
            "result_value": 27.0,
            "unit_of_measurement": null,
            "reference_range": "- 32.0"
        }
    ]
}