{
    "Date": "02.12.2023",
    "patient_information": {
        "patient_id": "01 23456789",
        "patient_name": "shivam bungalow s g road",
        "patient_sex": "male",
        "patient_age": "21 years"
    },
    "test_results": [
        {
            "test_name": "hemoglobin",
            "result_value": "12.5",
            "unit_of_measurement": "gbj",
            "reference_range": "13.0 17.0 gldl"
        },
        {
            "test_name": "RBC count total RBC",
            "result_value": "5.2",
            "unit_of_measurement": "45 55 millicumm",
            "reference_range": null
        },
        {
            "test_name": "Packed cell volume (PCV)",
            "result_value": "57.5",
            "unit_of_measurement": "",
            "reference_range": "40 50 oo"
        },
        {
            "test_name": "Mean corpuscular volume (MCV)",
            "result_value": "87.75",
            "unit_of_measurement": "fl",
            "reference_range": "83 101 fl"
        },
        {
            "test_name": "MCH",
            "result_value": "27.2",
            "unit_of_measurement": "pg",
            "reference_range": "27.1 32 pg"
        },
        {
            "test_name": "MCHC",
            "result_value": "82.8",
            "unit_of_measurement": "",
            "reference_range": "32 51 345 gidl"
        },
        {
            "test_name": "RDW",
            "result_value": "13.6",
            "unit_of_measurement": "",
            "reference_range": "11.6 14.0 oo"
        },
        {
            "test_name": "WBC count total WBC",
            "result_value": "9000",
            "unit_of_measurement": "count cumm",
            "reference_range": "4000 11000 count cumm"
        },
        {
            "test_name": "Neutrophils",
            "result_value": "50.62",
            "unit_of_measurement": "%",
            "reference_range": "60 00"
        },
        {
            "test_name": "Lymphocytes",
            "result_value": "31.20",
            "unit_of_measurement": "%",
            "reference_range": "40 0"
        },
        {
            "test_name": "Eosinophils",
            "result_value": "0.06",
            "unit_of_measurement": "%",
            "reference_range": "7.00"
        },
        {
            "test_name": "Monocytes",
            "result_value": "10.00",
            "unit_of_measurement": "%",
            "reference_range": null
        },
        {
            "test_name": "Basophils",
            "result_value": "0.02",
            "unit_of_measurement": "%",
            "reference_range": "0.02"
        },
        {
            "test_name": "Platelet count",
            "result_value": "150000",
            "unit_of_measurement": "",
            "reference_range": "410000"
        }
    ]
}