{
    "Date": null,
    "patient_information": {
        "patient_id": null,
        "patient_name": null,
        "patient_sex": null,
        "patient_age": null
    },
    "test_results": [
        {
            "test_name": "y O",
            "result_value": null,
            "unit_of_measurement": null,
            "reference_e ntire range": null
        },
        {
            "test_name": "a ro a p ca y Df # / A o / 1 / A go",
            "result_value": null,
            "unit_of_measurement": null,
            "reference_range": null
        }
    ]
}