{
    "Date": null,
    "patient_information": {
        "patient_id": null,
        "patient_name": null,
        "patient_sex": null,
        "patient_age": null
    },
    "test_results": [
        {
            "test_name": "Hemograma Leucocitaria JO 2 Formula",
            "result_value": null,
            "unit_of_measurement": null,
            "reference_range": null
        },
        {
            "test_name": "Eosinofilos VN",
            "result_value": "51",
            "unit_of_measurement": "%",
            "reference_range": "1-4%"
        },
        {
            "test_name": "Cayados 36 JUS Segmentados",
            "result_value": "55",
            "unit_of_measurement": "%",
            "reference_range": "45-75%"
        },
        {
            "test_name": "Globular 10",
            "result_value": "31",
            "unit_of_measurement": "%",
            "reference_range": "2-7%"
        },
        {
            "test_name": "JO O00 Linfocitos Recuento",
            "result_value": "1517",
            "unit_of_measurement": "/mm3",
            "reference_range": null
        },
        {
            "test_name": "MMI Monocitos OO0 44 Por LL Hematies Sedimentacion",
            "result_value": "O00",
            "unit_of_measurement": "g/dL",
            "reference_range": null
        },
        {
            "test_name": "Basofilos 148 SA0O0O Hematocrito OD Laogoo Yo 3270",
            "result_value": "12.70",
            "unit_of_measurement": "%",
            "reference_range": "37-50%"
        },
        {
            "test_name": "Hemoglobina De 981 2 Velocidad GIO 86 MMS OOO L Leucocitos 138 32P6 21 IMMS 887 Plaquetas Yo Hora 31 L 33 S 298 VCM Ven 336 Yo HCM MG 110 Serica 70 Yo CHCM MB 220 Bioquimica 150 Yo MS MB 65 35 87 Yo MY MG 140 Hasta 169 JO ME MB 150 Glucosa Hasta 60 Yo MS MB Colesterol 50 Hasta 6 100 25 Me M HDL 3171 45 MB Jo H NG LDL 160 19 50 Trigliceridos Yo MG 12 45 05 MMOLIL LY 546162 Urea 145 MB Jo Urico 82GR MMOLL 06 AC 62 Hierro 73.9 Creatinina VN 75 Homocisteina 4OuyL Enzimaticas T Hasta Proteinas JUYT A0 Hasta UL Pruebas UL 50 40 UL 11 A UL 43 GOT 45 NE Vo GPT MEQLL 145 GT 135 MEQIL Ionograma MEQL 110 98 MEQL Meqil 54 141 31 MEQL 98 Sodio 02 AT Cloro Potasio",
            "result_value": null,
            "unit_of_measurement": null,
            "reference_range": null
        }
    ]
}