{
    "Date": null,
    "patient_information": {
        "patient_id": null,
        "patient_name": null,
        "patient_sex": null,
        "patient_age": null
    },
    "test_results": [
        {
            "test_nmae": "Systolic Blood Pressure",
            "result_value": 120,
            "unit_of_measurement": "mmHg",
            "reference_range": null
        },
        {
            "test_name": "Diastol cuff pressure",
            "result_value": 80,
            "unit_of_measurement": "mmHg",
            "reference_range": null
        }
    ]
}