{
    "Date": "02/12/XX",
    "patient_information": {
        "patient_id": null,
        "patient_name": "MUMBH ACARE COMPLEA Dec.?",
        "patient_sex": "Male",
        "patient_age": 21
    },
    "test_results": [
        {
            "test_name": "(CBC) Ref.",
            "result_value": 57.5,
            "unit_of_measurement": "fL",
            "reference_range": "100-1719"
        },
        {
            "test_name": "Blood Cell Volumet Volurme",
            "result_value": 32.8,
            "unit_of_measurement": "%",
            "reference_range": null
        },
        {
            "test_name": "(PCV) (MCV)",
            "result_value": 34.5,
            "unit_of_measurement": "%",
            "reference_range": "27-32"
        },
        {
            "test_name": "RBC Total RBC SNDICES",
            "result_value": 272,
            "unit_of_measurement": null,
            "reference_range": null
        },
        {
            "test_name": "MCNG",
            "result_value": 9000,
            "unit_of_measurement": "00-06",
            "reference_range": null
        },
        {
            "test_name": "WBC COUNT",
            "result_value": 31000,
            "unit_of_measurement": "15000-41000",
            "reference_range": null
        }
    ]
}