{
    "Date": null,
    "patient_information": {
        "patient_id": "9e121",
        "patient_name": "io patel",
        "patient_sex": "saxi",
        "patient_age": null
    },
    "test_results": [
        {
            "test_name": "totad cownt t count",
            "result_value": 161,
            "unit_of_measurement": null,
            "reference_range": null
        },
        {
            "test_name": "onorycon icoc reterencevabe hocye e onooyted ocoowr ss",
            "result_value": 110,
            "unit_of_measurement": null,
            "reference_range": null
        },
        {
            "test_name": "platmutcoucy petehei",
            "result_value": 111,
            "unit_of_measurement": null,
            "reference_range": null
        },
        {
            "test_name": "cirrndax asaks praodeax t sao rxrmndex cowm b aass c b",
            "result_value": 22,
            "unit_of_measurement": null,
            "reference_range": null
        },
        {
            "test_name": "esacoeks 111 stt c 1a0 sooonto 4 s pmlti b mndwnes dbaln labyochnicien b sy q b",
            "result_value": 0,
            "unit_of_measurement": null,
            "reference_range": null
        },
        {
            "test_name": "0 0 b o q 1sooc 4toeco q t sogro q mapaticte moxtms 0128m1si paeteft",
            "result_value": 142,
            "unit_of_measurement": null,
            "reference_range": null
        }
    ]
}