{
    "Date": null,
    "patient_information": {
        "patient_id": "0912345678",
        "patient_name": "drlogypathlabadrlogy",
        "patient_sex": "male",
        "patient_age": null
    },
    "test_results": [
        {
            "test_name": "Pn",
            "result_value": "low",
            "unit_of_measurement": null,
            "reference_range": "105-135"
        },
        {
            "test_name": "Hemoglobin",
            "result_value": "125",
            "unit_of_measurement": null,
            "reference_range": "105-135"
        }
    ]
}