{
    "date_of_test": null,
    "patient_information": {
        "name": "Patel",
        "age": 52,
        "sex": null,
        "years": 125
    },
    "test_results": [
        {
            "test_name": "Hb",
            "result_value": 32.5,
            "unit_of_measurement": "g/dL",
            "reference_range": "27-45"
        },
        {
            "test_name": "MCV",
            "result_value": 14.0,
            "unit_of_measurement": "fL",
            "reference_range": null
        },
        {
            "test_name": "WBC",
            "result_value": null,
            "unit_of_measurement": null,
            "reference_range": null
        }
    ]
}