{
    "Date": null,
    "patient_information": {
        "patient_id": "170",
        "patient_name": "Shivam Patel",
        "patient_sex": "Male",
        "patient_age": 27
    },
    "test_results": [
        {
            "test_name": "Hemoglobin",
            "result_value": 13.5,
            "unit_of_measurement": "g/dL",
            "reference_range": null
        },
        {
            "test_name": "WBC Count",
            "result_value": 8775,
            "unit_of_measurement": "cells/µL",
            "reference_range": null
        }
    ]
}