{
    "Date": null,
    "patient_information": {
        "patient_id": null,
        "patient_name": null,
        "patient_sex": null,
        "patient_age": null
    },
    "test_results": [
        {
            "test_name": "lpetths",
            "result_value": "care",
            "unit_of_measurement": "ois",
            "reference_range": "cate"
        },
        {
            "test_name": "cadead",
            "result_value": "coa",
            "unit_of_measurement": "oto",
            "reference_range": "te"
        },
        {
            "test_name": "te roer",
            "result_value": "rketg",
            "unit_of_measurement": "sa",
            "reference_range": "dn"
        },
        {
            "test_name": "pa ras fo ds ce",
            "result_value": "ris giton",
            "unit_of_measurement": "osss",
            "reference_range": "a lolh"
        },
        {
            "test_name": "or sp hos leliii il desettes",
            "result_value": "fl ioj eelaters ted rn slotes",
            "unit_of_measurement": "l tanineg teabins la pu l ta ste sbabs ste cra as e ljoas tal casrol 51 dre lcain cans cd",
            "reference_range": "ictd m"
        },
        {
            "test_name": "m te tootes faere o lo o ve c urt c iseany cs tis nte fel pen t aracl cross dssores lo ce la ile t9 leerc",
            "result_value": null,
            "unit_of_measurement": null,
            "reference_range": null
        }
    ]
}