{
    "Date": null,
    "patient_information": {
        "patient_id": null,
        "patient_name": null,
        "patient_sex": null,
        "patient_age": null
    },
    "test_results": [
        {
            "test_name": "HEMOGRAMA SERIE ROJA",
            "result_value": "Hematies HEMOGLOBINA Hematocrito V.C.M, OEB/L gid %y iL",
            "unit_of_measurement": null,
            "reference_range": null
        },
        {
            "test_name": "HEMAGLOBIN",
            "result_value": "4.00",
            "unit_of_measurement": "%y",
            "reference_range": "4,00 - 12.0"
        },
        {
            "test_name": "V.C.M.",
            "result_value": "80.0",
            "unit_of_measurement": null,
            "reference_range": null
        },
        {
            "test_name": "OEB/L gid %y iL",
            "result_value": "5.50",
            "unit_of_measurement": null,
            "reference_range": null
        },
        {
            "test_name": "HEMATOCRITO",
            "result_value": "36.0",
            "unit_of_measurement": "%y",
            "reference_range": null
        },
        {
            "test_name": "V.C.M.",
            "result_value": "16.0",
            "unit_of_measurement": null,
            "reference_range": null
        },
        {
            "test_name": "OEB/L gid %y iL",
            "result_value": "47.0",
            "unit_of_measurement": null,
            "reference_range": null
        },
        {
            "test_name": "28.0",
            "result_value": "82.0",
            "unit_of_measurement": null,
            "reference_range": null
        }
    ]
}