{
    "Date": null,
    "patient_information": {
        "patient_id": null,
        "patient_name": "Yash M. Patel",
        "patient_sex": "n",
        "patient_age": "21"
    },
    "test_results": [
        {
            "test_name": "410000 unn 100001 4000-1100",
            "result_value": "32.5",
            "unit_of_measurement": "-34.5 Reference Valuee 27- 32",
            "reference_range": null
        },
        {
            "test_name": "13.0 - 17.0",
            "result_value": null,
            "unit_of_measurement": "4.5-5.5 n yb!H Ref.",
            "reference_range": "Dr. Hiren Shahe Drlogy pathology Lab Lab Techniciar."
        }
    ]
}