{
    "Date": "02 Dec 2022",
    "patient_information": {
        "patient_id": null,
        "patient_name": "Dr. Vimal Shah",
        "patient_sex": "Male",
        "patient_age": null
    },
    "test_results": [
        {
            "test_name": "Hemoglobin (Hb)",
            "result_value": 11.6,
            "unit_of_measurement": "%",
            "reference_range": "13.0 - 17.0"
        },
        {
            "test_name": "Red Blood Cell Count",
            "result_value": 4.5,
            "unit_of_measurement": "million per microliter",
            "reference_range": "3.8 - 5.2 million per microliter"
        },
        {
            "test_name": "Hematocrit",
            "result_value": 32.5,
            "unit_of_measurement": "%",
            "reference_range": "37 - 48%"
        },
        {
            "test_name": "Mean Corpuscular Volume (MCV)",
            "result_value": 90,
            "unit_of_measurement": "fl",
            "reference_range": "80 - 100 fl"
        },
        {
            "test_name": "Platelet Count",
            "result_value": 74,
            "unit_of_measurement": "thousand per microliter",
            "reference_range": "11.6 - 14.0 thousand per microliter"
        },
        {
            "test_name": "Neutrophils",
            "result_value": 83,
            "unit_of_measurement": "%",
            "reference_range": "50 - 62%"
        },
        {
            "test_name": "Lymphocytes",
            "result_value": 27,
            "unit_of_measurement": "%",
            "reference_range": "40 - 50%"
        },
        {
            "test_name": "Monocytes",
            "result_value": 13.6,
            "unit_of_measurement": "%",
            "reference_range": "0-10%"
        },
        {
            "test_name": "Eosinophils",
            "result_value": 6,
            "unit_of_measurement": "%",
            "reference_range": "0-5%"
        },
        {
            "test_name": "Basophils",
            "result_value": 1,
            "unit_of_measurement": "%",
            "reference_range": "0-1%"
        },
        {
            "test_name": "RDW",
            "result_value": 5.2,
            "unit_of_measurement": "",
            "reference_range": "14 - 15"
        }
    ]
}