{
    "Date": "02.12.202x",
    "patient_information": {
        "patient_id": "01234s6789",
        "patient_name": "patel",
        "patient_sex": "male",
        "patient_age": "21 years"
    },
    "test_results": [
        {
            "test_name": "hemoglobin",
            "result_value": "669576",
            "unit_of_measurement": "g/dL",
            "reference_range": null
        },
        {
            "test_name": "RBC count",
            "result_value": "125",
            "unit_of_measurement": "x 10^6/µL",
            "reference_range": "4.2-5.4 x 10^6/µL"
        },
        {
            "test_name": "Hb",
            "result_value": "6.69",
            "unit_of_measurement": "g/dL",
            "reference_range": null
        },
        {
            "test_name": "MCV",
            "result_value": "52",
            "unit_of_measurement": "fL",
            "reference_range": "80-100 fL"
        },
        {
            "test_name": "MCHC",
            "result_value": "35.1",
            "unit_of_measurement": "g/dL",
            "reference_range": null
        },
        {
            "test_name": "RDW",
            "result_value": "57.5",
            "unit_of_measurement": "%",
            "reference_range": "11.5-14.5%"
        },
        {
            "test_name": "WBC count",
            "result_value": "45",
            "unit_of_measurement": "x 10^3/µL",
            "reference_range": null
        },
        {
            "test_name": "Neutrophils",
            "result_value": "52",
            "unit_of_measurement": "%",
            "reference_range": null
        },
        {
            "test_name": "Lymphocytes",
            "result_value": "8",
            "unit_of_measurement": "%",
            "reference_range": null
        },
        {
            "test_name": "Monocytes",
            "result_value": "10",
            "unit_of_measurement": "%",
            "reference_range": null
        },
        {
            "test_name": "Eosinophils",
            "result_value": "6",
            "unit_of_measurement": "%",
            "reference_range": null
        },
        {
            "test_name": "Basophils",
            "result_value": "3.25",
            "unit_of_measurement": "%",
            "reference_range": null
        },
        {
            "test_name": "Platelets",
            "result_value": "140",
            "unit_of_measurement": "x 10^3/µL",
            "reference_range": null
        }
    ]
}