{
    "Date": null,
    "patient_information": {
        "patient_id": "0123456789",
        "patient_name": "Amn pmOGyRAncnoanp Camglortm - VahtPalel www.driogy.com [I I Cmmphecna Iah C.ten Cub Complete Blood Count li.. Iiliai I:.,l :: (CBC) polton s Vaali. f. ult Ilut",
        "patient_sex": null,
        "patient_age": null
    },
    "test_results": [
        {
            "test_name": "Complete Blood Count (CBC)",
            "result_value": "polton s Vaali.",
            "unit_of_measurement": null,
            "reference_range": "ult Ilut"
        }
    ]
}