{
    "Date": null,
    "patient_information": {
        "patient_id": null,
        "patient_name": null,
        "patient_sex": null,
        "patient_age": null
    },
    "test_results": [
        {
            "test_name": "HOLOgy",
            "result_value": "4567",
            "unit_of_measurement": null,
            "reference_range": null
        },
        {
            "test_name": "DrLOgy (coC)",
            "result_value": "Hr",
            "unit_of_measurement": null,
            "reference_range": null
        },
        {
            "test_name": "Ret.",
            "result_value": "ot!",
            "unit_of_measurement": null,
            "reference_range": null
        },
        {
            "test_name": "40 a.s",
            "result_value": "4A",
            "unit_of_measurement": null,
            "reference_range": null
        },
        {
            "test_name": "+ 11.6 : 10",
            "result_value": "8",
            "unit_of_measurement": null,
            "reference_range": null
        },
        {
            "test_name": "4",
            "result_value": null,
            "unit_of_measurement": null,
            "reference_range": null
        }
    ]
}