{
    "Date": "XX.XX.XXX",
    "patient_information": {
        "patient_id": null,
        "patient_name": "[Yasshmpatel]",
        "patient_sex": null,
        "patient_age": null
    },
    "test_results": [
        {
            "test_name": "Accurate Soswett drlogy Pathology",
            "result_value": null,
            "unit_of_measurement": "mosloon nco hoon oglotun in couun ozsasto totad ref coury carty byde onorpenhtabeanoicon rac a blooe stosonoed aplete oownx pached fa hironshan 042ot aso ffif",
            "reference_range": null
        },
        {
            "test_name": "Blood ca wohame ce cownt ipcn as cacl t sterenoey se oacn totad counnt sss tauee wec tpodeax pmedex",
            "result_value": null,
            "unit_of_measurement": "1105 orsrmndeax oouet te ropts 170 ma ss assbs ncoourt monooy n tiss soon blatiuit toy 72 cownr ss coumt nss",
            "reference_range": null
        },
        {
            "test_name": "Count",
            "result_value": null,
            "unit_of_measurement": "116 is aausto 1a0 sis nooglloos lost ab o b d b do b a mandwns 0 n o to pmallban q 10ooc technician",
            "reference_range": null
        },
        {
            "test_name": "Monooy",
            "result_value": null,
            "unit_of_measurement": "mapet mxceosrw 012 a sitzo isq",
            "reference_range": null
        }
    ]
}