{
    "Date": "02.12.2X",
    "patient_information": {
        "patient_id": null,
        "patient_name": "Yash M Patel",
        "patient_sex": "male",
        "patient_age": 21
    },
    "test_results": [
        {
            "test_name": "Peripheral Blood Smear Examination",
            "result_value": null,
            "unit_of_measurement": "N/A",
            "reference_range": null
        },
        {
            "test_name": "RBC Morphology",
            "result_value": "normocytic normochromic",
            "unit_of_measurement": "microscopy",
            "reference_range": "N/A"
        },
        {
            "test_name": "WBC Morphology",
            "result_value": "normal",
            "unit_eof_measurement": "microscopy",
            "reference_range": "N/A"
        },
        {
            "test_name": "Platelets",
            "result_value": "normal",
            "unit_of_measurement": "microscopy",
            "reference_range": null
        }
    ]
}