{
    "Date": null,
    "patient_information": {
        "patient_id": null,
        "patient_name": null,
        "patient_sex": null,
        "patient_age": null
    },
    "test_results": [
        {
            "test_name": "E 8 9",
            "result_value": "I D I : E I",
            "unit_of_measurement": "- I - Y 7",
            "reference_range": "N A N 8 8 8"
        },
        {
            "test_name": "a a 8 2",
            "result_value": "a 2 8 8 a",
            "unit_of_measurement": "E a a I I I o",
            "reference_range": "0o C L € a a a o a"
        },
        {
            "test_name": "a - a 3 a E",
            "result_value": "a 8 a S a",
            "unit_of_measurement": "- a - 8 LE 0 5 8 I I",
            "reference_range": "S 8 8 8 8 : U k a * E"
        },
        {
            "test_name": "of 1 a a E C E",
            "result_value": "9 9 e a a 8 2 o 8 5",
            "unit_of_measurement": "e 8 8 I 8 a e a - o",
            "reference_range": "a N : f f I I C 2"
        },
        {
            "test_name": "LO C a of o 00 I",
            "result_value": "e E I 8 f I 8 € I",
            "unit_of_measurement": "C a I € E a € I D",
            "reference_range": "I L C 0 8 - e 8 J"
        },
        {
            "test_name": "I E E 8 8 N 8 8 U",
            "result_value": "I 8 I C I 9 I I I € I 8",
            "unit_of_measurement": "I I I I I 0 I e - a D3",
            "reference_range": "€ € a a E S - - -"
        },
        {
            "test_name": "a I 2 € a I I C 8 C",
            "result_value": "E - 8 € 8 a ) I a : b s € L",
            "unit_of_measurement": "a 2 2 e 7 a = - 1 - C 2",
            "reference_range": "8 E 3 E E a 5 - -"
        },
        {
            "test_name": "a S à I € I L a 9",
            "result_value": "- : o E 4 D € C A - X L",
            "unit_of_measurement": "1 N Q C I 8 - I 8 y",
            "reference_range": "E I a - I 2 8 I I a - -"
        },
        {
            "test_name": "a - - € a - A 9 a : d",
            "result_value": "a N - a - 2 3 a a - - - E"
        }
    ]
}