{
    "Date": "02 Dec",
    "patient_information": {
        "patient_id": null,
        "patient_name": "Yash M. Patel",
        "patient_sex": "Male",
        "patient_age": 62
    },
    "test_results": [
        {
            "test_name": "BMI dic PLATELET Fu Fully aunr Eosin ogis oph",
            "result_value": 150000,
            "unit_of_measurement": "WBC COUNT",
            "reference_range": null
        },
        {
            "test_name": "WBC COUNT",
            "result_value": 10006,
            "unit_of_measurement": "",
            "reference_range": null
        },
        {
            "test_name": "RCC noglobin",
            "result_value": 150000,
            "unit_of_measurement": "(mcv) Volume count",
            "reference_range": null
        },
        {
            "test_name": "WBC RDW : Corpu",
            "result_value": 20,
            "unit_of_measurement": "",
            "reference_range": null
        },
        {
            "test_name": "WBC COUNT",
            "result_value": 13.0,
            "unit_of_measurement": "Range",
            "reference_range": "[8.5 - 14] "
        }
    ]
}