{
    "Date": null,
    "patient_information": {
        "patient_id": null,
        "patient_name": null,
        "patient_sex": null,
        "patient_age": null
    },
    "test_results": [
        {
            "test_name": "Creatinine",
            "result_value": 3,
            "unit_of_measurement": "%",
            "reference_range": "0.6-1.2"
        },
        {
            "test_name": "AST",
            "result_value": "a%",
            "unit_of_measurement": null,
            "reference_range": null
        },
        {
            "test_name": "ALT",
            "result_value": "a%",
            "unit_of_measurement": null,
            "reference_range": null
        },
        {
            "test_name": "Total Bilirubin",
            "result_value": "a%",
            "unit_of_measurement": null,
            "reference_range": null
        },
        {
            "test_name": "Direct Bilirubin",
            "result_value": "t%",
            "unit_of_measurement": null,
            "reference_range": null
        },
        {
            "test_name": "Urea",
            "result_value": "A 3 %",
            "unit_of_measurement": "%",
            "reference_range": null
        },
        {
            "test_name": "Albumin",
            "result_value": "3%",
            "unit_of_measurement": "%",
            "reference_range": "3.5-4.7"
        },
        {
            "test_name": ") a%",
            "result_value": "a%",
            "unit_of_measurement": null,
            "reference_range": null
        }
    ]
}