{
    "Date": "03 11 M. 02 Cec. 2X",
    "patient_information": {
        "patient_id": "FILL",
        "patient_name": "[FILL]",
        "patient_sex": "Male",
        "patient_age": "21 Years"
    },
    "test_results": [
        {
            "test_name": "Complete Blood Count (CBC)",
            "result_value": null,
            "unit_of_measurement": null,
            "reference_range": "[FILL] 32.5- 34.5 | [FILL] 13.0-17.0"
        },
        {
            "test_name": "Hemoglobin (Hb)",
            "result_value": "87.75",
            "unit_of_measurement": null,
            "reference_range": "90 : 00"
        },
        {
            "test_name": "Total RBC count",
            "result_value": null,
            "unit_of_measurement": null,
            "reference_range": "[FILL] 410000 | [FILL] 5.2"
        },
        {
            "test_name": "Platelet count",
            "result_value": null,
            "unit_of_measurement": null,
            "reference_range": "[FILL] 32.8 | [FILL] 150000"
        }
    ]
}