{
    "Date": null,
    "patient_information": {
        "patient_id": null,
        "patient_name": null,
        "patient_sex": null,
        "patient_age": null
    },
    "test_results": [
        {
            "test_name": "NEMOGLODINA B3-ga*",
            "result_value": 132,
            "unit_of_measurement": "4%",
            "reference_eange": null
        },
        {
            "test_name": "CHM.",
            "result_value": 83.4,
            "unit_of_measurement": "",
            "reference_range": ""
        },
        {
            "test_name": "O.E.",
            "result_value": 16.0,
            "unit_of_measurement": null,
            "reference_range": null
        }
    ]
}