{
    "Date": null,
    "patient_information": {
        "patient_id": null,
        "patient_name": "Cunm uwn",
        "patient_sex": null,
        "patient_age": "1P/6 mill/cumm o"
    },
    "test_results": [
        {
            "test_name": "PN 031 unt",
            "result_value": "150000",
            "unit_of_measurement": null,
            "reference_range": "4000-11000"
        },
        {
            "test_name": "11.6 - 14.0",
            "result_value": "13.0",
            "unit_of_measurement": "- 17.0",
            "reference_range": "Borderline Reference Value Z8-LZ"
        },
        {
            "test_name": "Complete Blood Count (CBC)",
            "result_value": "150000",
            "unit_of_measurement": null,
            "reference_range": "Anemia Drlogy pathology LAB Result alood PLATELET COUNT Primary Sample Type : HEMOGLOEN Investigation Yash M. Patel"
        },
        {
            "test_name": "PLATELET COUNT",
            "result_value": "150000",
            "unit_of_measurement": null,
            "reference_range": null
        }
    ]
}