{
    "Date": null,
    "patient_information": {
        "patient_id": null,
        "patient_name": null,
        "patient_sex": null,
        "patient_age": null
    },
    "test_results": [
        {
            "test_name": "Acctibate",
            "result_value": 4,
            "unit_of_measurement": "",
            "reference_range": ""
        },
        {
            "test_name": "TTT",
            "result_value": null,
            "unit_of_measurement": "",
            "reference_range": ""
        },
        {
            "test_name": "ev",
            "result_value": null,
            "unit_of_measurement": "",
            "reference_range": ""
        },
        {
            "test_name": "Fd",
            "result_value": null,
            "unit_of_measurement": "",
            "reference_range": ""
        },
        {
            "test_name": "CET",
            "result_value": null,
            "unit_of_measurement": "",
            "reference_range": ""
        },
        {
            "test_name": "ALT",
            "result_value": null,
            "unit_of_measurement": "",
            "reference_range": ""
        },
        {
            "test_name": "Techie",
            "result_value": "UU eee ALT Te a or LU",
            "unit_of_measurement": null,
            "reference_range": null
        }
    ]
}